crowdcount/__init__.py
crowdcount/data/__init__.py
crowdcount/data/data_loader/__init__.py
crowdcount/data/data_loader/crowd_dataset.py
crowdcount/data/data_loader/fudan_dataset.py
crowdcount/data/data_loader/shtu_dataset.py
crowdcount/data/data_loader/shtu_dataset_matlab.py
crowdcount/data/data_loader/ucf_cc_50.py
crowdcount/data/data_loader/ucf_qnrf.py
crowdcount/data/data_preprocess/__init__.py
crowdcount/data/data_preprocess/gaussian_filter.py
crowdcount/data/data_preprocess/preprocess.py
crowdcount/engine/__init__.py
crowdcount/engine/evaluate.py
crowdcount/engine/train.py
crowdcount/models/__init__.py
crowdcount/models/csr_net.py
crowdcount/models/mcnn.py
crowdcount/models/network.py
crowdcount/models/resnet101.py
crowdcount/models/resnet50.py
crowdcount/models/unet.py
crowdcount/models/vgg.py
crowdcount/transforms/__init__.py
crowdcount/transforms/transforms.py
crowdcount/utils/__init__.py
crowdcount/utils/loss.py
crowdcount/utils/optim.py
crowdcount/utils/saver.py
crowdcount/utils/tensorboard.py
crowdcount-0.1.1.dist-info/LICENSE
crowdcount-0.1.1.dist-info/METADATA
crowdcount-0.1.1.dist-info/WHEEL
crowdcount-0.1.1.dist-info/top_level.txt
crowdcount-0.1.1.dist-info/RECORD
