Metadata-Version: 2.1
Name: crowdcount
Version: 0.1.1
Summary: package for crowd counting
Home-page: https://github.com/FDU-VTS/crowd-count/
Author: Fudan-VTS
Author-email: sjchen18@fudan.edu.cn
License: UNKNOWN
Platform: UNKNOWN
Classifier: Programming Language :: Python :: 3
Classifier: License :: OSI Approved :: Apple Public Source License
Classifier: Operating System :: OS Independent
Requires-Python: >=3.6
